p22p/client.py
p22p/server.py
p22p/common.py
p22p/cli.py
p22p/__main__.py
p22p/client_gui.py
p22p/__init__.py
p22p-0.4.2.dist-info/metadata.json
p22p-0.4.2.dist-info/entry_points.txt
p22p-0.4.2.dist-info/DESCRIPTION.rst
p22p-0.4.2.dist-info/WHEEL
p22p-0.4.2.dist-info/METADATA
p22p-0.4.2.dist-info/top_level.txt
p22p-0.4.2.dist-info/RECORD
