Metadata-Version: 2.0
Name: p22p
Version: 0.4.2
Summary: Relay data between clients using a central server
Home-page: https://github.com/bennr01/p22p
Author: bennr01
Author-email: benjamin99.vogt@web.de
License: MIT
Keywords: network twisted relay proxy peer peer2peer
Platform: UNKNOWN
Classifier: Topic :: Utilities
Classifier: Development Status :: 4 - Beta
Classifier: Programming Language :: Python :: 2
Classifier: Programming Language :: Python :: 2.7
Requires-Dist: Twisted (>=17.1.0)
